basicai/__init__.py
basicai-0.1.dist-info/LICENSE.md
basicai-0.1.dist-info/METADATA
basicai-0.1.dist-info/WHEEL
basicai-0.1.dist-info/top_level.txt
basicai-0.1.dist-info/RECORD
