Metadata-Version: 2.1
Name: basicai
Version: 0.1
Summary: ...
Home-page: http://github.com/dejanbatanjac/basicai
Author: Dejan Batanjac
Author-email: dejan.batanjac@gmail.com
License: Apache 2.0
Platform: UNKNOWN
Requires-Dist: torch (>=1.0)
Requires-Dist: numpy
